{"data": {"map_v2": {"origin_city": {"iata": "DAD"}, "prices": [{"price": {"value": 38589.49}, "destination_city": {"iata": "TYO", "country": {"iata": "JP"}, "coordinates": {"lat": 35.6894875, "lon": 139.6917064}}, "travel_restrictions": null}, {"price": {"value": 2597}, "destination_city": {"iata": "PQC", "country": {"iata": "VN"}, "coordinates": {"lat": 10.223722, "lon": 103.96324}}, "travel_restrictions": null}, {"price": {"value": 2872}, "destination_city": {"iata": "SGN", "country": {"iata": "VN"}, "coordinates": {"lat": 10.813045, "lon": 106.662476}}, "travel_restrictions": null}, {"price": {"value": 2999}, "destination_city": {"iata": "DLI", "country": {"iata": "VN"}, "coordinates": {"lat": 11.749689, "lon": 108.37603}}, "travel_restrictions": null}, {"price": {"value": 3037}, "destination_city": {"iata": "NHA", "country": {"iata": "VN"}, "coordinates": {"lat": 12.2387911, "lon": 109.1967488}}, "travel_restrictions": null}, {"price": {"value": 3631.88}, "destination_city": {"iata": "HAN", "country": {"iata": "VN"}, "coordinates": {"lat": 21.214184, "lon": 105.802826}}, "travel_restrictions": null}, {"price": {"value": 4214}, "destination_city": {"iata": "CNX", "country": {"iata": "TH"}, "coordinates": {"lat": 18.769573, "lon": 98.96841}}, "travel_restrictions": null}, {"price": {"value": 4700.67}, "destination_city": {"iata": "KUL", "country": {"iata": "MY"}, "coordinates": {"lat": 3.139003, "lon": 101.686855}}, "travel_restrictions": null}, {"price": {"value": 4774.28}, "destination_city": {"iata": "HPH", "country": {"iata": "VN"}, "coordinates": {"lat": 20.823315, "lon": 106.727325}}, "travel_restrictions": null}, {"price": {"value": 4934}, "destination_city": {"iata": "BKK", "country": {"iata": "TH"}, "coordinates": {"lat": 13.7234186, "lon": 100.4762319}}, "travel_restrictions": null}, {"price": {"value": 5701}, "destination_city": {"iata": "SEL", "country": {"iata": "KR"}, "coordinates": {"lat": 37.566535, "lon": 126.9779692}}, "travel_restrictions": null}, {"price": {"value": 10686}, "destination_city": {"iata": "VTE", "country": {"iata": "LA"}, "coordinates": {"lat": 17.975431, "lon": 102.56772}}, "travel_restrictions": null}, {"price": {"value": 9574}, "destination_city": {"iata": "HKG", "country": {"iata": "HK"}, "coordinates": {"lat": 22.2478599, "lon": 114.2033843}}, "travel_restrictions": null}, {"price": {"value": 14199.83}, "destination_city": {"iata": "REP", "country": {"iata": "KH"}, "coordinates": {"lat": 13.408436, "lon": 103.815926}}, "travel_restrictions": null}, {"price": {"value": 5858}, "destination_city": {"iata": "PUS", "country": {"iata": "KR"}, "coordinates": {"lat": 35.179317, "lon": 128.94873}}, "travel_restrictions": null}, {"price": {"value": 8531}, "destination_city": {"iata": "SIN", "country": {"iata": "SG"}, "coordinates": {"lat": 1.2894365, "lon": 103.8499802}}, "travel_restrictions": null}]}}}