{"data": {"map_v2": {"origin_city": {"iata": "DYG"}, "prices": [{"price": {"value": 18629.04}, "destination_city": {"iata": "BJS", "country": {"iata": "CN"}, "coordinates": {"lat": 39.904214, "lon": 116.407413}}, "travel_restrictions": null}, {"price": {"value": 12181}, "destination_city": {"iata": "CTU", "country": {"iata": "CN"}, "coordinates": {"lat": 30.581135, "lon": 103.9568}}, "travel_restrictions": null}, {"price": {"value": 18326.78}, "destination_city": {"iata": "SHA", "country": {"iata": "CN"}, "coordinates": {"lat": 31.230393, "lon": 121.473704}}, "travel_restrictions": null}]}}}