{"data": {"map_v2": {"origin_city": {"iata": "KHV"}, "prices": [{"price": {"value": 50437}, "destination_city": {"iata": "HKT", "country": {"iata": "TH"}, "coordinates": {"lat": 8.107619, "lon": 98.306435}}, "travel_restrictions": null}, {"price": {"value": 3700}, "destination_city": {"iata": "BQS", "country": {"iata": "RU"}, "coordinates": {"lat": 50.416668, "lon": 127.4}}, "travel_restrictions": null}, {"price": {"value": 4243}, "destination_city": {"iata": "UUS", "country": {"iata": "RU"}, "coordinates": {"lat": 46.966667, "lon": 142.75}}, "travel_restrictions": null}, {"price": {"value": 4537.33}, "destination_city": {"iata": "NGK", "country": {"iata": "RU"}, "coordinates": {"lat": 51.8, "lon": 143.16667}}, "travel_restrictions": null}, {"price": {"value": 4635}, "destination_city": {"iata": "EKS", "country": {"iata": "RU"}, "coordinates": {"lat": 49.190735, "lon": 142.077703}}, "travel_restrictions": null}, {"price": {"value": 4735}, "destination_city": {"iata": "NER", "country": {"iata": "RU"}, "coordinates": {"lat": 56.65, "lon": 124.6}}, "travel_restrictions": null}, {"price": {"value": 4750}, "destination_city": {"iata": "KXK", "country": {"iata": "RU"}, "coordinates": {"lat": 50.4, "lon": 136.95}}, "travel_restrictions": null}, {"price": {"value": 5840}, "destination_city": {"iata": "OHH", "country": {"iata": "RU"}, "coordinates": {"lat": 53.516666, "lon": 142.88333}}, "travel_restrictions": null}, {"price": {"value": 6202}, "destination_city": {"iata": "GVN", "country": {"iata": "RU"}, "coordinates": {"lat": 48.9575, "lon": 140.2811111}}, "travel_restrictions": null}, {"price": {"value": 7100.73}, "destination_city": {"iata": "\u0417\u0415\u042f", "country": {"iata": "RU"}, "coordinates": {"lat": 53.689724, "lon": 127.09222}}, "travel_restrictions": null}, {"price": {"value": 7562.22}, "destination_city": {"iata": "TYD", "country": {"iata": "RU"}, "coordinates": {"lat": 55.283333, "lon": 124.73333}}, "travel_restrictions": null}, {"price": {"value": 8300}, "destination_city": {"iata": "HTA", "country": {"iata": "RU"}, "coordinates": {"lat": 52.033333, "lon": 113.3}}, "travel_restrictions": null}, {"price": {"value": 9003}, "destination_city": {"iata": "\u0425\u0420\u041f", "country": {"iata": "RU"}, "coordinates": {"lat": 52.9749985, "lon": 138.81667}}, "travel_restrictions": null}, {"price": {"value": 9355}, "destination_city": {"iata": "UUD", "country": {"iata": "RU"}, "coordinates": {"lat": 51.833332, "lon": 107.5}}, "travel_restrictions": null}, {"price": {"value": 9358}, "destination_city": {"iata": "NLI", "country": {"iata": "RU"}, "coordinates": {"lat": 53.15, "lon": 140.73333}}, "travel_restrictions": null}, {"price": {"value": 9408}, "destination_city": {"iata": "BQG", "country": {"iata": "RU"}, "coordinates": {"lat": 52.378334, "lon": 140.44833}}, "travel_restrictions": null}, {"price": {"value": 9465}, "destination_city": {"iata": "VVO", "country": {"iata": "RU"}, "coordinates": {"lat": 43.378574, "lon": 132.14075}}, "travel_restrictions": null}, {"price": {"value": 10500}, "destination_city": {"iata": "DYR", "country": {"iata": "RU"}, "coordinates": {"lat": 64.73333, "lon": 177.75}}, "travel_restrictions": null}, {"price": {"value": 10670}, "destination_city": {"iata": "YKS", "country": {"iata": "RU"}, "coordinates": {"lat": 62.085606, "lon": 129.75006}}, "travel_restrictions": null}, {"price": {"value": 11332}, "destination_city": {"iata": "HRB", "country": {"iata": "CN"}, "coordinates": {"lat": 45.620853, "lon": 126.23644}}, "travel_restrictions": null}, {"price": {"value": 11801}, "destination_city": {"iata": "IKT", "country": {"iata": "RU"}, "coordinates": {"lat": 52.273308, "lon": 104.35607}}, "travel_restrictions": null}, {"price": {"value": 12136}, "destination_city": {"iata": "PKC", "country": {"iata": "RU"}, "coordinates": {"lat": 53.016666, "lon": 158.65}}, "travel_restrictions": null}, {"price": {"value": 12745.73}, "destination_city": {"iata": "\u041d\u041b\u041d", "country": {"iata": "RU"}, "coordinates": {"lat": 57.6416664, "lon": 136.16167}}, "travel_restrictions": null}, {"price": {"value": 13393.19}, "destination_city": {"iata": "OHO", "country": {"iata": "RU"}, "coordinates": {"lat": 59.416668, "lon": 143.05}}, "travel_restrictions": null}, {"price": {"value": 14337}, "destination_city": {"iata": "BJS", "country": {"iata": "CN"}, "coordinates": {"lat": 39.904214, "lon": 116.407413}}, "travel_restrictions": null}, {"price": {"value": 15505}, "destination_city": {"iata": "MOW", "country": {"iata": "RU"}, "coordinates": {"lat": 55.755786, "lon": 37.617633}}, "travel_restrictions": null}, {"price": {"value": 17450}, "destination_city": {"iata": "LED", "country": {"iata": "RU"}, "coordinates": {"lat": 59.939039, "lon": 30.315785}}, "travel_restrictions": null}, {"price": {"value": 17549}, "destination_city": {"iata": "GDX", "country": {"iata": "RU"}, "coordinates": {"lat": 59.916668, "lon": 150.71666}}, "travel_restrictions": null}, {"price": {"value": 20775.93}, "destination_city": {"iata": "SVX", "country": {"iata": "RU"}, "coordinates": {"lat": 56.750336, "lon": 60.804314}}, "travel_restrictions": null}, {"price": {"value": 21163}, "destination_city": {"iata": "OVB", "country": {"iata": "RU"}, "coordinates": {"lat": 55.00901, "lon": 82.667}}, "travel_restrictions": null}, {"price": {"value": 21499}, "destination_city": {"iata": "KJA", "country": {"iata": "RU"}, "coordinates": {"lat": 56.18113, "lon": 92.48286}}, "travel_restrictions": null}, {"price": {"value": 28825}, "destination_city": {"iata": "ULN", "country": {"iata": "MN"}, "coordinates": {"lat": 47.85275, "lon": 106.76327}}, "travel_restrictions": null}]}}}