{"data": {"map_v2": {"origin_city": {"iata": "SXB"}, "prices": [{"price": {"value": 37734}, "destination_city": {"iata": "TLS", "country": {"iata": "FR"}, "coordinates": {"lat": 43.63007, "lon": 1.374321}}, "travel_restrictions": null}, {"price": {"value": 4508}, "destination_city": {"iata": "NCE", "country": {"iata": "FR"}, "coordinates": {"lat": 43.66049, "lon": 7.205232}}, "travel_restrictions": null}, {"price": {"value": 4643.73}, "destination_city": {"iata": "FRA", "country": {"iata": "DE"}, "coordinates": {"lat": 50.050735, "lon": 8.570773}}, "travel_restrictions": null}, {"price": {"value": 4797.24}, "destination_city": {"iata": "BIQ", "country": {"iata": "FR"}, "coordinates": {"lat": 43.472416, "lon": -1.531242}}, "travel_restrictions": null}, {"price": {"value": 6797}, "destination_city": {"iata": "MPL", "country": {"iata": "FR"}, "coordinates": {"lat": 43.610769, "lon": 3.876716}}, "travel_restrictions": null}, {"price": {"value": 8036.37}, "destination_city": {"iata": "BCN", "country": {"iata": "ES"}, "coordinates": {"lat": 41.387917, "lon": 2.1699187}}, "travel_restrictions": null}, {"price": {"value": 11719.38}, "destination_city": {"iata": "BOD", "country": {"iata": "FR"}, "coordinates": {"lat": 44.837789, "lon": -0.57918}}, "travel_restrictions": null}, {"price": {"value": 11857}, "destination_city": {"iata": "IST", "country": {"iata": "TR"}, "coordinates": {"lat": 40.976665, "lon": 28.815277}}, "travel_restrictions": null}, {"price": {"value": 16313.45}, "destination_city": {"iata": "OPO", "country": {"iata": "PT"}, "coordinates": {"lat": 41.149968, "lon": -8.6102426}}, "travel_restrictions": null}, {"price": {"value": 17157}, "destination_city": {"iata": "LYS", "country": {"iata": "FR"}, "coordinates": {"lat": 45.764043, "lon": 4.835659}}, "travel_restrictions": null}, {"price": {"value": 27931}, "destination_city": {"iata": "CMN", "country": {"iata": "MA"}, "coordinates": {"lat": 33.533333, "lon": -7.583333}}, "travel_restrictions": null}]}}}