{"data": {"map_v2": {"origin_city": {"iata": "TCI"}, "prices": [{"price": {"value": 61909.04}, "destination_city": {"iata": "CCS", "country": {"iata": "VE"}, "coordinates": {"lat": 10.596942, "lon": -67.00551}}, "travel_restrictions": null}, {"price": {"value": 10810.93}, "destination_city": {"iata": "CAS", "country": {"iata": "MA"}, "coordinates": {"lat": 33.533333, "lon": -7.58333}}, "travel_restrictions": null}, {"price": {"value": 17875.23}, "destination_city": {"iata": "PRG", "country": {"iata": "CZ"}, "coordinates": {"lat": 50.0878114, "lon": 14.4204598}}, "travel_restrictions": null}, {"price": {"value": 1818.6}, "destination_city": {"iata": "AGA", "country": {"iata": "MA"}, "coordinates": {"lat": 30.378326, "lon": -9.555895}}, "travel_restrictions": null}, {"price": {"value": 17805.58}, "destination_city": {"iata": "SDR", "country": {"iata": "ES"}, "coordinates": {"lat": 43.4609602, "lon": -3.8079336}}, "travel_restrictions": null}, {"price": {"value": 18013.35}, "destination_city": {"iata": "STR", "country": {"iata": "DE"}, "coordinates": {"lat": 48.7771056, "lon": 9.1807688}}, "travel_restrictions": null}, {"price": {"value": 10902.82}, "destination_city": {"iata": "BGO", "country": {"iata": "NO"}, "coordinates": {"lat": 60.3912628, "lon": 5.3220544}}, "travel_restrictions": null}, {"price": {"value": 1922.89}, "destination_city": {"iata": "VLC", "country": {"iata": "ES"}, "coordinates": {"lat": 39.4907322, "lon": -0.4558824}}, "travel_restrictions": null}, {"price": {"value": 18065.39}, "destination_city": {"iata": "MUC", "country": {"iata": "DE"}, "coordinates": {"lat": 48.1391265, "lon": 11.5801863}}, "travel_restrictions": null}, {"price": {"value": 2208.34}, "destination_city": {"iata": "SVQ", "country": {"iata": "ES"}, "coordinates": {"lat": 37.38264, "lon": -5.9962951}}, "travel_restrictions": null}, {"price": {"value": 10998.43}, "destination_city": {"iata": "VIE", "country": {"iata": "AT"}, "coordinates": {"lat": 48.2081743, "lon": 16.3738189}}, "travel_restrictions": null}, {"price": {"value": 18190.57}, "destination_city": {"iata": "OSL", "country": {"iata": "NO"}, "coordinates": {"lat": 59.9138688, "lon": 10.7522454}}, "travel_restrictions": null}, {"price": {"value": 11068.33}, "destination_city": {"iata": "SVG", "country": {"iata": "NO"}, "coordinates": {"lat": 58.9699756, "lon": 5.7331073}}, "travel_restrictions": null}, {"price": {"value": 2513.72}, "destination_city": {"iata": "BCN", "country": {"iata": "ES"}, "coordinates": {"lat": 41.387917, "lon": 2.1699187}}, "travel_restrictions": null}, {"price": {"value": 19345.52}, "destination_city": {"iata": "XRY", "country": {"iata": "ES"}, "coordinates": {"lat": 36.6865618, "lon": -6.1371725}}, "travel_restrictions": null}, {"price": {"value": 11164.9}, "destination_city": {"iata": "FNC", "country": {"iata": "PT"}, "coordinates": {"lat": 32.693123, "lon": -16.775635}}, "travel_restrictions": null}, {"price": {"value": 2669.88}, "destination_city": {"iata": "ALC", "country": {"iata": "ES"}, "coordinates": {"lat": 38.34521, "lon": -0.4809945}}, "travel_restrictions": null}, {"price": {"value": 11357.07}, "destination_city": {"iata": "TLS", "country": {"iata": "FR"}, "coordinates": {"lat": 43.63007, "lon": 1.374321}}, "travel_restrictions": null}, {"price": {"value": 19586.68}, "destination_city": {"iata": "VGO", "country": {"iata": "ES"}, "coordinates": {"lat": 42.2313564, "lon": -8.7124471}}, "travel_restrictions": null}, {"price": {"value": 3062.48}, "destination_city": {"iata": "MAD", "country": {"iata": "ES"}, "coordinates": {"lat": 40.4166909, "lon": -3.7003454}}, "travel_restrictions": null}, {"price": {"value": 11549.57}, "destination_city": {"iata": "STO", "country": {"iata": "SE"}, "coordinates": {"lat": 59.3327881, "lon": 18.0644881}}, "travel_restrictions": null}, {"price": {"value": 11867.47}, "destination_city": {"iata": "BIO", "country": {"iata": "ES"}, "coordinates": {"lat": 43.2569629, "lon": -2.9234409}}, "travel_restrictions": null}, {"price": {"value": 3093.02}, "destination_city": {"iata": "LPA", "country": {"iata": "ES"}, "coordinates": {"lat": 27.938944, "lon": -15.389351}}, "travel_restrictions": null}, {"price": {"value": 20219}, "destination_city": {"iata": "EDI", "country": {"iata": "GB"}, "coordinates": {"lat": 55.9501755, "lon": -3.1875359}}, "travel_restrictions": null}, {"price": {"value": 12159}, "destination_city": {"iata": "ANR", "country": {"iata": "BE"}, "coordinates": {"lat": 51.21992, "lon": 4.39625}}, "travel_restrictions": null}, {"price": {"value": 3175.27}, "destination_city": {"iata": "AGP", "country": {"iata": "ES"}, "coordinates": {"lat": 36.7196484, "lon": -4.4200163}}, "travel_restrictions": null}, {"price": {"value": 21107.98}, "destination_city": {"iata": "HAM", "country": {"iata": "DE"}, "coordinates": {"lat": 53.553813, "lon": 9.991586}}, "travel_restrictions": null}, {"price": {"value": 13123.81}, "destination_city": {"iata": "BRU", "country": {"iata": "BE"}, "coordinates": {"lat": 50.8503396, "lon": 4.3517103}}, "travel_restrictions": null}, {"price": {"value": 21855.89}, "destination_city": {"iata": "FRA", "country": {"iata": "DE"}, "coordinates": {"lat": 50.050735, "lon": 8.570773}}, "travel_restrictions": null}, {"price": {"value": 3199.05}, "destination_city": {"iata": "PMI", "country": {"iata": "ES"}, "coordinates": {"lat": 39.547653, "lon": 2.730388}}, "travel_restrictions": null}, {"price": {"value": 14979.52}, "destination_city": {"iata": "ZAZ", "country": {"iata": "ES"}, "coordinates": {"lat": 41.66386, "lon": -1.007466}}, "travel_restrictions": null}, {"price": {"value": 22753.71}, "destination_city": {"iata": "VNO", "country": {"iata": "LT"}, "coordinates": {"lat": 54.643078, "lon": 25.279606}}, "travel_restrictions": null}, {"price": {"value": 3333.1}, "destination_city": {"iata": "OPO", "country": {"iata": "PT"}, "coordinates": {"lat": 41.149968, "lon": -8.6102426}}, "travel_restrictions": null}, {"price": {"value": 15358.75}, "destination_city": {"iata": "CGN", "country": {"iata": "DE"}, "coordinates": {"lat": 50.9406645, "lon": 6.9599115}}, "travel_restrictions": null}, {"price": {"value": 3585.38}, "destination_city": {"iata": "BOD", "country": {"iata": "FR"}, "coordinates": {"lat": 44.837789, "lon": -0.57918}}, "travel_restrictions": null}, {"price": {"value": 15718.33}, "destination_city": {"iata": "AMS", "country": {"iata": "NL"}, "coordinates": {"lat": 52.3730556, "lon": 4.8922222}}, "travel_restrictions": null}, {"price": {"value": 27209.64}, "destination_city": {"iata": "DUB", "country": {"iata": "IE"}, "coordinates": {"lat": 53.42728, "lon": -6.24357}}, "travel_restrictions": null}, {"price": {"value": 15784.41}, "destination_city": {"iata": "CPH", "country": {"iata": "DK"}, "coordinates": {"lat": 55.693403, "lon": 12.583046}}, "travel_restrictions": null}, {"price": {"value": 3668.5}, "destination_city": {"iata": "SCQ", "country": {"iata": "ES"}, "coordinates": {"lat": 42.897316, "lon": -8.420327}}, "travel_restrictions": null}, {"price": {"value": 27683.68}, "destination_city": {"iata": "NUE", "country": {"iata": "DE"}, "coordinates": {"lat": 49.45052, "lon": 11.08048}}, "travel_restrictions": null}, {"price": {"value": 16019}, "destination_city": {"iata": "HAJ", "country": {"iata": "DE"}, "coordinates": {"lat": 52.3720683, "lon": 9.7356861}}, "travel_restrictions": null}, {"price": {"value": 30235.75}, "destination_city": {"iata": "LEJ", "country": {"iata": "DE"}, "coordinates": {"lat": 51.43, "lon": 12.24}}, "travel_restrictions": null}, {"price": {"value": 16182.71}, "destination_city": {"iata": "HEL", "country": {"iata": "FI"}, "coordinates": {"lat": 60.2943605, "lon": 25.0402427}}, "travel_restrictions": null}, {"price": {"value": 30822.15}, "destination_city": {"iata": "RIX", "country": {"iata": "LV"}, "coordinates": {"lat": 56.92208, "lon": 23.979807}}, "travel_restrictions": null}, {"price": {"value": 16265.64}, "destination_city": {"iata": "OST", "country": {"iata": "BE"}, "coordinates": {"lat": 51.2166667, "lon": 2.9}}, "travel_restrictions": null}, {"price": {"value": 3777.04}, "destination_city": {"iata": "SPC", "country": {"iata": "ES"}, "coordinates": {"lat": 28.626389, "lon": -17.755556}}, "travel_restrictions": null}, {"price": {"value": 16970.47}, "destination_city": {"iata": "GRX", "country": {"iata": "ES"}, "coordinates": {"lat": 37.1764874, "lon": -3.5979291}}, "travel_restrictions": null}, {"price": {"value": 32424.03}, "destination_city": {"iata": "REK", "country": {"iata": "IS"}, "coordinates": {"lat": 64.135338, "lon": -21.89521}}, "travel_restrictions": null}, {"price": {"value": 17324.35}, "destination_city": {"iata": "DUS", "country": {"iata": "DE"}, "coordinates": {"lat": 51.2249429, "lon": 6.7756524}}, "travel_restrictions": null}, {"price": {"value": 4008.14}, "destination_city": {"iata": "LIS", "country": {"iata": "PT"}, "coordinates": {"lat": 38.706932, "lon": -9.1356321}}, "travel_restrictions": null}, {"price": {"value": 19586.68}, "destination_city": {"iata": "ZRH", "country": {"iata": "CH"}, "coordinates": {"lat": 47.367347, "lon": 8.5500025}}, "travel_restrictions": null}, {"price": {"value": 4234.84}, "destination_city": {"iata": "GMZ", "country": {"iata": "ES"}, "coordinates": {"lat": 28.016666, "lon": -17.2}}, "travel_restrictions": null}, {"price": {"value": 51255}, "destination_city": {"iata": "TLL", "country": {"iata": "EE"}, "coordinates": {"lat": 59.4388619, "lon": 24.7544715}}, "travel_restrictions": null}, {"price": {"value": 36380.5}, "destination_city": {"iata": "LUX", "country": {"iata": "LU"}, "coordinates": {"lat": 49.63111, "lon": 6.209539}}, "travel_restrictions": null}, {"price": {"value": 6962}, "destination_city": {"iata": "ROM", "country": {"iata": "IT"}, "coordinates": {"lat": 41.8905198, "lon": 12.4942486}}, "travel_restrictions": null}, {"price": {"value": 7025.99}, "destination_city": {"iata": "LYS", "country": {"iata": "FR"}, "coordinates": {"lat": 45.764043, "lon": 4.835659}}, "travel_restrictions": null}, {"price": {"value": 5630.08}, "destination_city": {"iata": "MIL", "country": {"iata": "IT"}, "coordinates": {"lat": 45.463681, "lon": 9.1881714}}, "travel_restrictions": null}, {"price": {"value": 5961.04}, "destination_city": {"iata": "VCE", "country": {"iata": "IT"}, "coordinates": {"lat": 45.4343363, "lon": 12.3387844}}, "travel_restrictions": null}, {"price": {"value": 7334}, "destination_city": {"iata": "NTE", "country": {"iata": "FR"}, "coordinates": {"lat": 47.218371, "lon": -1.553621}}, "travel_restrictions": null}, {"price": {"value": 4331.09}, "destination_city": {"iata": "VDE", "country": {"iata": "ES"}, "coordinates": {"lat": 27.813969, "lon": -17.884937}}, "travel_restrictions": null}, {"price": {"value": 5976.34}, "destination_city": {"iata": "PAR", "country": {"iata": "FR"}, "coordinates": {"lat": 48.856614, "lon": 2.3522219}}, "travel_restrictions": null}, {"price": {"value": 6885.55}, "destination_city": {"iata": "OVD", "country": {"iata": "ES"}, "coordinates": {"lat": 43.55891, "lon": -6.032094}}, "travel_restrictions": null}, {"price": {"value": 7488.69}, "destination_city": {"iata": "ACE", "country": {"iata": "ES"}, "coordinates": {"lat": 28.950668, "lon": -13.609059}}, "travel_restrictions": null}, {"price": {"value": 4821.36}, "destination_city": {"iata": "MRS", "country": {"iata": "FR"}, "coordinates": {"lat": 43.296482, "lon": 5.36978}}, "travel_restrictions": null}, {"price": {"value": 4754.05}, "destination_city": {"iata": "FUE", "country": {"iata": "ES"}, "coordinates": {"lat": 28.450605, "lon": -13.869893}}, "travel_restrictions": null}, {"price": {"value": 6905.95}, "destination_city": {"iata": "BUD", "country": {"iata": "HU"}, "coordinates": {"lat": 47.4984056, "lon": 19.0407578}}, "travel_restrictions": null}, {"price": {"value": 9451.79}, "destination_city": {"iata": "LON", "country": {"iata": "GB"}, "coordinates": {"lat": 51.51, "lon": 0.06}}, "travel_restrictions": null}, {"price": {"value": 9412.24}, "destination_city": {"iata": "WAW", "country": {"iata": "PL"}, "coordinates": {"lat": 52.170906, "lon": 20.97329}}, "travel_restrictions": null}, {"price": {"value": 9469.19}, "destination_city": {"iata": "BUH", "country": {"iata": "RO"}, "coordinates": {"lat": 44.437711, "lon": 26.097367}}, "travel_restrictions": null}, {"price": {"value": 9843}, "destination_city": {"iata": "LIL", "country": {"iata": "FR"}, "coordinates": {"lat": 50.62925, "lon": 3.057256}}, "travel_restrictions": null}, {"price": {"value": 8568.82}, "destination_city": {"iata": "GDN", "country": {"iata": "PL"}, "coordinates": {"lat": 54.380978, "lon": 18.468655}}, "travel_restrictions": null}, {"price": {"value": 8746}, "destination_city": {"iata": "BER", "country": {"iata": "DE"}, "coordinates": {"lat": 52.5234051, "lon": 13.4113999}}, "travel_restrictions": null}]}}}