[{"iata": "IST", "min_price": 2925.63, "lat": 40.976665, "lng": 28.815277}, {"iata": "AYT", "min_price": 19065.35, "lat": 36.89928, "lng": 30.80135}, {"iata": "MIL", "min_price": 3097.44, "lat": 45.463681, "lng": 9.1881714}, {"iata": "ROM", "min_price": 4682.8, "lat": 41.8905198, "lng": 12.4942486}, {"iata": "CTA", "min_price": 5028, "lat": 37.47066, "lng": 15.065877}, {"iata": "VCE", "min_price": 5823.24, "lat": 45.4343363, "lng": 12.3387844}, {"iata": "BRU", "min_price": 3151.01, "lat": 50.8503396, "lng": 4.3517103}, {"iata": "LON", "min_price": 3344.07, "lat": 51.51, "lng": 0.06}, {"iata": "PAR", "min_price": 3490.5, "lat": 48.856614, "lng": 2.3522219}, {"iata": "CPH", "min_price": 5096.5, "lat": 55.693403, "lng": 12.583046}, {"iata": "BCN", "min_price": 6907.41, "lat": 41.387917, "lng": 2.1699187}, {"iata": "LCA", "min_price": 6426.94, "lat": 34.880867, "lng": 33.62599}, {"iata": "DTM", "min_price": 8032.47, "lat": 51.514828, "lng": 7.613139}, {"iata": "EAP", "min_price": 8501.62, "lat": 47.752, "lng": 7.336}, {"iata": "VIE", "min_price": 12903.68, "lat": 48.2081743, "lng": 16.3738189}]