[{"iata": "UTP", "min_price": 6419.57, "lat": 12.683333, "lng": 101.01667}, {"iata": "HKT", "min_price": 7285, "lat": 8.107619, "lng": 98.306435}, {"iata": "BKK", "min_price": 7319.07, "lat": 13.7234186, "lng": 100.4762319}, {"iata": "KBV", "min_price": 8719.28, "lat": 8.097281, "lng": 98.98062}, {"iata": "CNX", "min_price": 9661, "lat": 18.769573, "lng": 98.96841}, {"iata": "SIN", "min_price": 10523.81, "lat": 1.2894365, "lng": 103.8499802}, {"iata": "HKG", "min_price": 21032.33, "lat": 22.2478599, "lng": 114.2033843}]